vstransitions/__init__.py
vstransitions/_metadata.py
vstransitions/easing.py
vstransitions/fade.py
vstransitions/panning.py
vstransitions/py.typed
vstransitions-0.1.3.dist-info/METADATA
vstransitions-0.1.3.dist-info/WHEEL
vstransitions-0.1.3.dist-info/licenses/LICENSE
vstransitions-0.1.3.dist-info/RECORD
